geomagindices/__init__.py
geomagindices/__main__.py
geomagindices/base.py
geomagindices/dataio.py
geomagindices/web.py
geomagindices/data/May2016Rpt.txt
geomagindices/data/__init__.py
geomagindices/tests/test_read.py
geomagindices-1.5.1.dist-info/LICENSE.txt
geomagindices-1.5.1.dist-info/METADATA
geomagindices-1.5.1.dist-info/WHEEL
geomagindices-1.5.1.dist-info/top_level.txt
geomagindices-1.5.1.dist-info/RECORD
