Metadata-Version: 2.1
Name: geomagindices
Version: 1.5.1
Summary: Download and parse geomagnetic indices
Keywords: aeronomy,ionosphere
Classifier: Development Status :: 5 - Production/Stable
Classifier: Environment :: Console
Classifier: Intended Audience :: Science/Research
Classifier: Operating System :: OS Independent
Classifier: Programming Language :: Python :: 3
Classifier: Topic :: Scientific/Engineering :: Atmospheric Science
Requires-Python: >=3.9
License-File: LICENSE.txt
Requires-Dist: python-dateutil
Requires-Dist: pandas
Requires-Dist: requests
Requires-Dist: numpy
Provides-Extra: tests
Requires-Dist: pytest; extra == "tests"
Provides-Extra: lint
Requires-Dist: flake8; extra == "lint"
Requires-Dist: flake8-bugbear; extra == "lint"
Requires-Dist: flake8-builtins; extra == "lint"
Requires-Dist: flake8-blind-except; extra == "lint"
Requires-Dist: mypy; extra == "lint"
Requires-Dist: types-requests; extra == "lint"
Requires-Dist: types-python-dateutil; extra == "lint"
